dr14tmeter2024/__init__.py
dr14tmeter2024/__main__.py
dr14tmeter2024/audio_analysis.py
dr14tmeter2024/audio_decoder.py
dr14tmeter2024/audio_file_reader.py
dr14tmeter2024/audio_math.py
dr14tmeter2024/audio_track.py
dr14tmeter2024/compressor.py
dr14tmeter2024/compute_dr.py
dr14tmeter2024/compute_dr14.py
dr14tmeter2024/compute_drv.py
dr14tmeter2024/database.py
dr14tmeter2024/database_utils.py
dr14tmeter2024/dr14_config.py
dr14tmeter2024/dr14_global.py
dr14tmeter2024/dr14_tmeter.py
dr14tmeter2024/dr14_utils.py
dr14tmeter2024/dr_histogram.py
dr14tmeter2024/duration.py
dr14tmeter2024/dynamic_range_meter.py
dr14tmeter2024/dynamic_vivacity.py
dr14tmeter2024/lev_histogram.py
dr14tmeter2024/my_time_formatter.py
dr14tmeter2024/out_messages.py
dr14tmeter2024/parse_args.py
dr14tmeter2024/plot_track.py
dr14tmeter2024/plot_track_classic.py
dr14tmeter2024/query.py
dr14tmeter2024/read_metadata.py
dr14tmeter2024/spectrogram.py
dr14tmeter2024/table.py
dr14tmeter2024/tagger.py
dr14tmeter2024/wav_write.py
dr14tmeter2024/write_dr.py
dr14tmeter2024-0.5.0.dist-info/LICENSE
dr14tmeter2024-0.5.0.dist-info/METADATA
dr14tmeter2024-0.5.0.dist-info/WHEEL
dr14tmeter2024-0.5.0.dist-info/entry_points.txt
dr14tmeter2024-0.5.0.dist-info/RECORD
