Metadata-Version: 2.1
Name: dr14tmeter2024
Version: 0.5.0
Summary: Cloned from https://github.com/simon-r/dr14_t.meter
Home-page: https://gitlab.com/francispotter/dr14_tmeter
License: MIT
Author: Simone Riva
Requires-Python: >=3.11,<3.12
Classifier: License :: OSI Approved :: MIT License
Classifier: Programming Language :: Python :: 3
Classifier: Programming Language :: Python :: 3.11
Requires-Dist: mutagen (>=1.47.0,<2.0.0)
Requires-Dist: numpy (>=2.1.1,<3.0.0)
Project-URL: Repository, https://gitlab.com/francispotter/dr14_tmeter
